ovos_stt_plugin_citrinet/__init__.py
ovos_stt_plugin_citrinet/engine.py
ovos_stt_plugin_citrinet/version.py
ovos_stt_plugin_citrinet-0.1.0.dist-info/licenses/LICENSE
ovos_stt_plugin_citrinet-0.1.0.dist-info/METADATA
ovos_stt_plugin_citrinet-0.1.0.dist-info/WHEEL
ovos_stt_plugin_citrinet-0.1.0.dist-info/entry_points.txt
ovos_stt_plugin_citrinet-0.1.0.dist-info/top_level.txt
ovos_stt_plugin_citrinet-0.1.0.dist-info/zip-safe
ovos_stt_plugin_citrinet-0.1.0.dist-info/RECORD
