Metadata-Version: 2.4
Name: ovos-stt-plugin-citrinet
Version: 0.1.0
Summary: A citrinet stt plugin for mycroft
Home-page: https://github.com/OpenVoiceOS/ovos-stt-plugin-citrinet
Author: JarbasAi
Author-email: jarbasai@mailfence.com
License: Apache-2.0
Keywords: ovos plugin stt
Classifier: Development Status :: 3 - Alpha
Classifier: Intended Audience :: Developers
Classifier: License :: OSI Approved :: Apache Software License
License-File: LICENSE
Requires-Dist: ovos-plugin-manager<3.0.0,>=2.1.0
Requires-Dist: ovos-utils>=0.0.30,~=0.0
Requires-Dist: SpeechRecognition~=3.8
Requires-Dist: torch>=1.13.1
Requires-Dist: onnxruntime
Requires-Dist: sentencepiece
Requires-Dist: huggingface-hub
Requires-Dist: numpy<2.0.0
Provides-Extra: resampling
Requires-Dist: soxr; extra == "resampling"
Dynamic: author
Dynamic: author-email
Dynamic: classifier
Dynamic: home-page
Dynamic: keywords
Dynamic: license
Dynamic: license-file
Dynamic: provides-extra
Dynamic: requires-dist
Dynamic: summary
